gyukutai/__init__.py
gyukutai-1.0.0.dist-info/DESCRIPTION.rst
gyukutai-1.0.0.dist-info/METADATA
gyukutai-1.0.0.dist-info/RECORD
gyukutai-1.0.0.dist-info/WHEEL
gyukutai-1.0.0.dist-info/metadata.json
gyukutai-1.0.0.dist-info/top_level.txt
