Metadata-Version: 2.0
Name: gyukutai
Version: 1.0.0
Summary: Hurting CPython deeply
Home-page: https://github.com/SunDwarf/gyukutai.git
Author: Laura Dickinson
Author-email: l@veriny.tf
License: MIT
Platform: UNKNOWN
Requires-Dist: forbiddenfruit
